pytwoway/__init__.py
pytwoway/cre.py
pytwoway/fe_approximate_correction_full.py
pytwoway/twfe_network.py
pytwoway_pkg-0.0.1.dist-info/LICENSE
pytwoway_pkg-0.0.1.dist-info/METADATA
pytwoway_pkg-0.0.1.dist-info/WHEEL
pytwoway_pkg-0.0.1.dist-info/top_level.txt
pytwoway_pkg-0.0.1.dist-info/RECORD
