Metadata-Version: 2.1
Name: pytwoway-pkg
Version: 0.0.1
Summary: Two way fixed effect models in python
Home-page: https://github.com/tlamadon/pytwoway
Author: Thibaut Lamadon, Adam Alexander Oppenheimer
Author-email: thibaut.lamadon@gmail.com
Maintainer: Thibaut Lamadon
License: Apache Software License 
Project-URL: Documentation, https://github.com/tlamadon/pytwoway
Project-URL: Source, https://github.com/tlamadon/pytwoway
Project-URL: Tracker, https://github.com/tlamadon/pytwoway/issues
Keywords: sparse,two way fixed effects
Platform: UNKNOWN
Classifier: Development Status :: 2 - Pre-Alpha 
Classifier: Operating System :: OS Independent
Classifier: License :: OSI Approved :: Apache Software License
Classifier: Topic :: Scientific/Engineering :: Mathematics
Classifier: Programming Language :: Python
Classifier: Programming Language :: Python :: 3
Classifier: Programming Language :: Python :: 3.6
Classifier: Programming Language :: Python :: 3.7
Classifier: Intended Audience :: Developers
Classifier: Intended Audience :: Science/Research
Requires-Python: >=3.6
Requires-Dist: numpy
Requires-Dist: pandas
Requires-Dist: networkx (>=2.3)
Requires-Dist: sklearn
Requires-Dist: scipy
Requires-Dist: pyamg
Requires-Dist: pyreadr
Requires-Dist: tqdm
Requires-Dist: decorator
